ipsw_parser/__init__.py
ipsw_parser/__main__.py
ipsw_parser/_version.py
ipsw_parser/build_identity.py
ipsw_parser/build_manifest.py
ipsw_parser/component.py
ipsw_parser/exceptions.py
ipsw_parser/firmware.py
ipsw_parser/ipsw.py
ipsw_parser-1.4.3.dist-info/licenses/LICENSE
ipsw_parser-1.4.3.dist-info/METADATA
ipsw_parser-1.4.3.dist-info/WHEEL
ipsw_parser-1.4.3.dist-info/entry_points.txt
ipsw_parser-1.4.3.dist-info/top_level.txt
ipsw_parser-1.4.3.dist-info/RECORD
