Metadata-Version: 2.4
Name: ipsw-parser
Version: 1.4.3
Summary: python3 utility for parsing and extracting data from IPSW
Author-email: doronz88 <doron88@gmail.com>
Maintainer-email: doronz88 <doron88@gmail.com>
License:                     GNU GENERAL PUBLIC LICENSE
Project-URL: Homepage, https://github.com/doronz88/ipsw_parser
Project-URL: Bug Reports, https://github.com/doronz88/ipsw_parser/issues
Keywords: ios,cli,firmware,ipsw
Classifier: Development Status :: 5 - Production/Stable
Classifier: License :: OSI Approved :: GNU General Public License v3 or later (GPLv3+)
Classifier: Programming Language :: Python :: 3
Classifier: Programming Language :: Python :: 3.9
Classifier: Programming Language :: Python :: 3.10
Classifier: Programming Language :: Python :: 3.11
Classifier: Programming Language :: Python :: 3.12
Classifier: Programming Language :: Python :: 3.13
Classifier: Programming Language :: Python :: 3 :: Only
Requires-Python: >=3.9
License-File: LICENSE
Requires-Dist: construct>=2.9.29
Requires-Dist: click
Requires-Dist: coloredlogs
Requires-Dist: cached_property
Requires-Dist: plumbum
Requires-Dist: pyimg4>=0.8.8
Requires-Dist: requests
Requires-Dist: remotezip2
Provides-Extra: test
Requires-Dist: pytest; extra == "test"
Dynamic: license-file
